qiskit_addon_utils/__init__.py
qiskit_addon_utils/coloring/__init__.py
qiskit_addon_utils/coloring/automatic_coloring.py
qiskit_addon_utils/coloring/validation.py
qiskit_addon_utils/exp_vals/__init__.py
qiskit_addon_utils/exp_vals/expectation_values.py
qiskit_addon_utils/exp_vals/measurement_bases.py
qiskit_addon_utils/exp_vals/observable_mappings.py
qiskit_addon_utils/noise_management/__init__.py
qiskit_addon_utils/noise_management/constants.py
qiskit_addon_utils/noise_management/gamma_factor.py
qiskit_addon_utils/noise_management/trex_factors.py
qiskit_addon_utils/noise_management/post_selection/__init__.py
qiskit_addon_utils/noise_management/post_selection/post_selection_summary.py
qiskit_addon_utils/noise_management/post_selection/post_selector.py
qiskit_addon_utils/noise_management/post_selection/transpiler/__init__.py
qiskit_addon_utils/noise_management/post_selection/transpiler/passes/__init__.py
qiskit_addon_utils/noise_management/post_selection/transpiler/passes/add_post_selection_measures.py
qiskit_addon_utils/noise_management/post_selection/transpiler/passes/add_spectator_measures.py
qiskit_addon_utils/noise_management/post_selection/transpiler/passes/utils.py
qiskit_addon_utils/noise_management/post_selection/transpiler/passes/xslow_gate.py
qiskit_addon_utils/problem_generators/__init__.py
qiskit_addon_utils/problem_generators/generate_time_evolution_circuit.py
qiskit_addon_utils/problem_generators/generate_xyz_hamiltonian.py
qiskit_addon_utils/slicing/__init__.py
qiskit_addon_utils/slicing/combine_slices.py
qiskit_addon_utils/slicing/slice_by_barriers.py
qiskit_addon_utils/slicing/slice_by_coloring.py
qiskit_addon_utils/slicing/slice_by_depth.py
qiskit_addon_utils/slicing/slice_by_gate_types.py
qiskit_addon_utils/slicing/transpiler/__init__.py
qiskit_addon_utils/slicing/transpiler/passes/__init__.py
qiskit_addon_utils/slicing/transpiler/passes/collect_op_color.py
qiskit_addon_utils/slicing/transpiler/passes/collect_op_size.py
qiskit_addon_utils-0.3.0.dist-info/METADATA
qiskit_addon_utils-0.3.0.dist-info/WHEEL
qiskit_addon_utils-0.3.0.dist-info/licenses/LICENSE.txt
qiskit_addon_utils-0.3.0.dist-info/RECORD
