Metadata-Version: 2.4
Name: qiskit-addon-utils
Version: 0.3.0
Summary: Utilities to support workflows leveraging Qiskit addons
License-Expression: Apache-2.0
License-File: LICENSE.txt
Classifier: Intended Audience :: Developers
Classifier: Intended Audience :: Science/Research
Classifier: License :: OSI Approved :: Apache Software License
Classifier: Natural Language :: English
Classifier: Operating System :: MacOS
Classifier: Operating System :: Microsoft :: Windows
Classifier: Operating System :: POSIX :: Linux
Classifier: Programming Language :: Python :: 3.9
Classifier: Programming Language :: Python :: 3.10
Classifier: Programming Language :: Python :: 3.11
Classifier: Programming Language :: Python :: 3.12
Classifier: Programming Language :: Python :: 3.13
Classifier: Topic :: Scientific/Engineering :: Physics
Requires-Python: >=3.9
Requires-Dist: numpy>=1.23
Requires-Dist: qiskit<3,>=2.1
Requires-Dist: rustworkx>=0.15
Provides-Extra: basetest
Requires-Dist: pytest-cov>=5.0; extra == 'basetest'
Requires-Dist: pytest>=8.0; extra == 'basetest'
Provides-Extra: dev
Requires-Dist: ipywidgets; extra == 'dev'
Requires-Dist: jupyter-sphinx; extra == 'dev'
Requires-Dist: matplotlib; extra == 'dev'
Requires-Dist: mypy==1.18.2; extra == 'dev'
Requires-Dist: nbmake>=1.5.0; extra == 'dev'
Requires-Dist: nbqa>=1.8.5; extra == 'dev'
Requires-Dist: nbsphinx>=0.9.4; extra == 'dev'
Requires-Dist: pylatexenc; extra == 'dev'
Requires-Dist: pylint==3.3.9; extra == 'dev'
Requires-Dist: pytest-cov>=5.0; extra == 'dev'
Requires-Dist: pytest-doctestplus>=1.2.1; extra == 'dev'
Requires-Dist: pytest>=8.0; extra == 'dev'
Requires-Dist: qiskit-ibm-runtime; extra == 'dev'
Requires-Dist: qiskit-qasm3-import>=0.5.0; extra == 'dev'
Requires-Dist: qiskit-sphinx-theme~=2.0.0; extra == 'dev'
Requires-Dist: reno>=4.1; extra == 'dev'
Requires-Dist: ruff==0.14.3; extra == 'dev'
Requires-Dist: rustworkx[graphviz]>=0.15; extra == 'dev'
Requires-Dist: sphinx-autodoc-typehints; extra == 'dev'
Requires-Dist: sphinx-copybutton; extra == 'dev'
Requires-Dist: sphinx-design; extra == 'dev'
Requires-Dist: sphinx-reredirects; extra == 'dev'
Requires-Dist: tox>=4.4.3; extra == 'dev'
Requires-Dist: typos>=1.20.0; extra == 'dev'
Provides-Extra: docs
Requires-Dist: ipywidgets; extra == 'docs'
Requires-Dist: jupyter-sphinx; extra == 'docs'
Requires-Dist: matplotlib; extra == 'docs'
Requires-Dist: nbsphinx>=0.9.4; extra == 'docs'
Requires-Dist: pylatexenc; extra == 'docs'
Requires-Dist: pytest-cov>=5.0; extra == 'docs'
Requires-Dist: pytest-doctestplus>=1.2.1; extra == 'docs'
Requires-Dist: pytest>=8.0; extra == 'docs'
Requires-Dist: qiskit-ibm-runtime; extra == 'docs'
Requires-Dist: qiskit-sphinx-theme~=2.0.0; extra == 'docs'
Requires-Dist: reno>=4.1; extra == 'docs'
Requires-Dist: rustworkx[graphviz]>=0.15; extra == 'docs'
Requires-Dist: sphinx-autodoc-typehints; extra == 'docs'
Requires-Dist: sphinx-copybutton; extra == 'docs'
Requires-Dist: sphinx-design; extra == 'docs'
Requires-Dist: sphinx-reredirects; extra == 'docs'
Provides-Extra: doctest
Requires-Dist: ipywidgets; extra == 'doctest'
Requires-Dist: matplotlib; extra == 'doctest'
Requires-Dist: pylatexenc; extra == 'doctest'
Requires-Dist: pytest-cov>=5.0; extra == 'doctest'
Requires-Dist: pytest-doctestplus>=1.2.1; extra == 'doctest'
Requires-Dist: pytest>=8.0; extra == 'doctest'
Requires-Dist: qiskit-ibm-runtime; extra == 'doctest'
Requires-Dist: rustworkx[graphviz]>=0.15; extra == 'doctest'
Provides-Extra: lint
Requires-Dist: mypy==1.18.2; extra == 'lint'
Requires-Dist: nbqa>=1.8.5; extra == 'lint'
Requires-Dist: pylint==3.3.9; extra == 'lint'
Requires-Dist: reno>=4.1; extra == 'lint'
Requires-Dist: ruff==0.14.3; extra == 'lint'
Requires-Dist: typos>=1.20.0; extra == 'lint'
Provides-Extra: nbtest
Requires-Dist: nbmake>=1.5.0; extra == 'nbtest'
Requires-Dist: pytest-cov>=5.0; extra == 'nbtest'
Requires-Dist: pytest>=8.0; extra == 'nbtest'
Provides-Extra: notebook-dependencies
Requires-Dist: ipywidgets; extra == 'notebook-dependencies'
Requires-Dist: matplotlib; extra == 'notebook-dependencies'
Requires-Dist: pylatexenc; extra == 'notebook-dependencies'
Requires-Dist: qiskit-ibm-runtime; extra == 'notebook-dependencies'
Requires-Dist: rustworkx[graphviz]>=0.15; extra == 'notebook-dependencies'
Provides-Extra: style
Requires-Dist: nbqa>=1.8.5; extra == 'style'
Requires-Dist: ruff==0.14.3; extra == 'style'
Requires-Dist: typos>=1.20.0; extra == 'style'
Provides-Extra: test
Requires-Dist: pytest-cov>=5.0; extra == 'test'
Requires-Dist: pytest>=8.0; extra == 'test'
Requires-Dist: qiskit-qasm3-import>=0.5.0; extra == 'test'
